pyloadapi/__init__.py
pyloadapi/api.py
pyloadapi/cli.py
pyloadapi/exceptions.py
pyloadapi/py.typed
pyloadapi/types.py
pyloadapi-1.4.2.dist-info/METADATA
pyloadapi-1.4.2.dist-info/WHEEL
pyloadapi-1.4.2.dist-info/entry_points.txt
pyloadapi-1.4.2.dist-info/licenses/AUTHORS.md
pyloadapi-1.4.2.dist-info/licenses/LICENSE
pyloadapi-1.4.2.dist-info/RECORD
