Metadata-Version: 2.4
Name: PyLoadAPI
Version: 1.4.2
Summary: Simple wrapper for pyLoad's API.
Project-URL: Documentation, https://tr4nt0r.github.io/pyloadapi
Project-URL: Source, https://github.com/tr4nt0r/pyloadapi
Author-email: Manfred Dennerlein Rodelo <manfred@dennerlein.name>
License-Expression: MIT
License-File: AUTHORS.md
License-File: LICENSE
Classifier: Operating System :: OS Independent
Classifier: Programming Language :: Python :: 3
Requires-Python: >=3.11
Requires-Dist: aiohttp~=3.9
Provides-Extra: cli
Requires-Dist: click; extra == 'cli'
